{
    "PlayerInfo": {
        "PokemonList": [
            {
                "_info": {
                    "instanceID": 30254
                },
                "_individualValue": 17,
                "_hp": 11,
                "_maxHp": 11,
                "_attack": 12,
                "_block": 12,
                "_speed": 12,
                "_skillList": [
                    {
                        "instanceID": 30268
                    },
                    {
                        "instanceID": 0
                    },
                    {
                        "instanceID": 0
                    },
                    {
                        "instanceID": 0
                    }
                ],
                "_level": 1,
                "_curExp": 0,
                "_maxExp": 7,
                "_CurAccExp": 1,
                "_befAccExp": 0,
                "_NexAccExp": 8,
                "_name": "파이리"
            },
            {
                "_info": {
                    "instanceID": 0
                },
                "_individualValue": 0,
                "_hp": 0,
                "_maxHp": 0,
                "_attack": 0,
                "_block": 0,
                "_speed": 0,
                "_skillList": [
                    {
                        "instanceID": 0
                    },
                    {
                        "instanceID": 0
                    },
                    {
                        "instanceID": 0
                    },
                    {
                        "instanceID": 0
                    }
                ],
                "_level": 0,
                "_curExp": 0,
                "_maxExp": 0,
                "_CurAccExp": 0,
                "_befAccExp": 0,
                "_NexAccExp": 0,
                "_name": ""
            },
            {
                "_info": {
                    "instanceID": 0
                },
                "_individualValue": 0,
                "_hp": 0,
                "_maxHp": 0,
                "_attack": 0,
                "_block": 0,
                "_speed": 0,
                "_skillList": [
                    {
                        "instanceID": 0
                    },
                    {
                        "instanceID": 0
                    },
                    {
                        "instanceID": 0
                    },
                    {
                        "instanceID": 0
                    }
                ],
                "_level": 0,
                "_curExp": 0,
                "_maxExp": 0,
                "_CurAccExp": 0,
                "_befAccExp": 0,
                "_NexAccExp": 0,
                "_name": ""
            },
            {
                "_info": {
                    "instanceID": 0
                },
                "_individualValue": 0,
                "_hp": 0,
                "_maxHp": 0,
                "_attack": 0,
                "_block": 0,
                "_speed": 0,
                "_skillList": [
                    {
                        "instanceID": 0
                    },
                    {
                        "instanceID": 0
                    },
                    {
                        "instanceID": 0
                    },
                    {
                        "instanceID": 0
                    }
                ],
                "_level": 0,
                "_curExp": 0,
                "_maxExp": 0,
                "_CurAccExp": 0,
                "_befAccExp": 0,
                "_NexAccExp": 0,
                "_name": ""
            },
            {
                "_info": {
                    "instanceID": 0
                },
                "_individualValue": 0,
                "_hp": 0,
                "_maxHp": 0,
                "_attack": 0,
                "_block": 0,
                "_speed": 0,
                "_skillList": [
                    {
                        "instanceID": 0
                    },
                    {
                        "instanceID": 0
                    },
                    {
                        "instanceID": 0
                    },
                    {
                        "instanceID": 0
                    }
                ],
                "_level": 0,
                "_curExp": 0,
                "_maxExp": 0,
                "_CurAccExp": 0,
                "_befAccExp": 0,
                "_NexAccExp": 0,
                "_name": ""
            },
            {
                "_info": {
                    "instanceID": 0
                },
                "_individualValue": 0,
                "_hp": 0,
                "_maxHp": 0,
                "_attack": 0,
                "_block": 0,
                "_speed": 0,
                "_skillList": [
                    {
                        "instanceID": 0
                    },
                    {
                        "instanceID": 0
                    },
                    {
                        "instanceID": 0
                    },
                    {
                        "instanceID": 0
                    }
                ],
                "_level": 0,
                "_curExp": 0,
                "_maxExp": 0,
                "_CurAccExp": 0,
                "_befAccExp": 0,
                "_NexAccExp": 0,
                "_name": ""
            }
        ],
        "position": {
            "x": 0.0,
            "y": 1.0,
            "z": 0.0
        }
    },
    "EnemyInfo": {
        "PokemonList": [
            {
                "_info": {
                    "instanceID": 0
                },
                "_individualValue": 0,
                "_hp": 0,
                "_maxHp": 0,
                "_attack": 0,
                "_block": 0,
                "_speed": 0,
                "_skillList": [
                    {
                        "instanceID": 0
                    },
                    {
                        "instanceID": 0
                    },
                    {
                        "instanceID": 0
                    },
                    {
                        "instanceID": 0
                    }
                ],
                "_level": 0,
                "_curExp": 0,
                "_maxExp": 0,
                "_CurAccExp": 0,
                "_befAccExp": 0,
                "_NexAccExp": 0,
                "_name": ""
            },
            {
                "_info": {
                    "instanceID": 0
                },
                "_individualValue": 0,
                "_hp": 0,
                "_maxHp": 0,
                "_attack": 0,
                "_block": 0,
                "_speed": 0,
                "_skillList": [
                    {
                        "instanceID": 0
                    },
                    {
                        "instanceID": 0
                    },
                    {
                        "instanceID": 0
                    },
                    {
                        "instanceID": 0
                    }
                ],
                "_level": 0,
                "_curExp": 0,
                "_maxExp": 0,
                "_CurAccExp": 0,
                "_befAccExp": 0,
                "_NexAccExp": 0,
                "_name": ""
            },
            {
                "_info": {
                    "instanceID": 0
                },
                "_individualValue": 0,
                "_hp": 0,
                "_maxHp": 0,
                "_attack": 0,
                "_block": 0,
                "_speed": 0,
                "_skillList": [
                    {
                        "instanceID": 0
                    },
                    {
                        "instanceID": 0
                    },
                    {
                        "instanceID": 0
                    },
                    {
                        "instanceID": 0
                    }
                ],
                "_level": 0,
                "_curExp": 0,
                "_maxExp": 0,
                "_CurAccExp": 0,
                "_befAccExp": 0,
                "_NexAccExp": 0,
                "_name": ""
            },
            {
                "_info": {
                    "instanceID": 0
                },
                "_individualValue": 0,
                "_hp": 0,
                "_maxHp": 0,
                "_attack": 0,
                "_block": 0,
                "_speed": 0,
                "_skillList": [
                    {
                        "instanceID": 0
                    },
                    {
                        "instanceID": 0
                    },
                    {
                        "instanceID": 0
                    },
                    {
                        "instanceID": 0
                    }
                ],
                "_level": 0,
                "_curExp": 0,
                "_maxExp": 0,
                "_CurAccExp": 0,
                "_befAccExp": 0,
                "_NexAccExp": 0,
                "_name": ""
            },
            {
                "_info": {
                    "instanceID": 0
                },
                "_individualValue": 0,
                "_hp": 0,
                "_maxHp": 0,
                "_attack": 0,
                "_block": 0,
                "_speed": 0,
                "_skillList": [
                    {
                        "instanceID": 0
                    },
                    {
                        "instanceID": 0
                    },
                    {
                        "instanceID": 0
                    },
                    {
                        "instanceID": 0
                    }
                ],
                "_level": 0,
                "_curExp": 0,
                "_maxExp": 0,
                "_CurAccExp": 0,
                "_befAccExp": 0,
                "_NexAccExp": 0,
                "_name": ""
            },
            {
                "_info": {
                    "instanceID": 0
                },
                "_individualValue": 0,
                "_hp": 0,
                "_maxHp": 0,
                "_attack": 0,
                "_block": 0,
                "_speed": 0,
                "_skillList": [
                    {
                        "instanceID": 0
                    },
                    {
                        "instanceID": 0
                    },
                    {
                        "instanceID": 0
                    },
                    {
                        "instanceID": 0
                    }
                ],
                "_level": 0,
                "_curExp": 0,
                "_maxExp": 0,
                "_CurAccExp": 0,
                "_befAccExp": 0,
                "_NexAccExp": 0,
                "_name": ""
            }
        ],
        "position": {
            "x": 0.0,
            "y": 1.0,
            "z": 0.0
        }
    },
    "isWildPokemon": true,
    "wildPokemon": {
        "_info": {
            "instanceID": 30254
        },
        "_individualValue": 12,
        "_hp": 78,
        "_maxHp": 78,
        "_attack": 87,
        "_block": 81,
        "_speed": 97,
        "_skillList": [
            {
                "instanceID": 0
            },
            {
                "instanceID": 0
            },
            {
                "instanceID": 0
            },
            {
                "instanceID": 0
            }
        ],
        "_level": 36,
        "_curExp": 42875,
        "_maxExp": 3997,
        "_CurAccExp": 46656,
        "_befAccExp": 42875,
        "_NexAccExp": 50653,
        "_name": "파이리"
    }
}